lpci/__init__.py
lpci/evaluate.py
lpci/lpci.py
lpci-0.1.0.dist-info/LICENSE
lpci-0.1.0.dist-info/METADATA
lpci-0.1.0.dist-info/WHEEL
lpci-0.1.0.dist-info/RECORD
