Metadata-Version: 2.1
Name: lpci
Version: 0.1.0
Summary: This is a package to implement the LPCI algorithm for a regression forecasting model.
License: MIT
Author: BenSeimon
Author-email: benjamin.seimon@bse.eu
Requires-Python: >=3.10,<4.0
Classifier: License :: OSI Approved :: MIT License
Classifier: Programming Language :: Python :: 3
Classifier: Programming Language :: Python :: 3.10
Classifier: Programming Language :: Python :: 3.11
Classifier: Programming Language :: Python :: 3.12
Requires-Dist: black (>=24.10.0,<25.0.0)
Requires-Dist: pandas (>=2.0.0)
Requires-Dist: panelsplit (>=0.4.2,<0.5.0)
Requires-Dist: pylint (>=3.3.1,<4.0.0)
Requires-Dist: seaborn (>=0.13.2,<0.14.0)
Requires-Dist: sklearn-quantile (>=0.0.30)
